{
  "_fv": 43,
  "_type": "plant",
  "definition": {
    "renderType": 12,
    "texture": "spiritplant_new",
    "textureBottom": "",
    "customModelName": "Cross model",
    "itemTexture": "spiritplant_new_item",
    "particleTexture": "par2",
    "tintType": "No tint",
    "isItemTinted": false,
    "plantType": "normal",
    "staticPlantGenerationType": "Flower",
    "suspiciousStewEffect": "SPEED",
    "suspiciousStewDuration": 100,
    "growapableSpawnType": "Cave",
    "growapableMaxHeight": 3,
    "doublePlantGenerationType": "Flower",
    "customBoundingBox": false,
    "disableOffset": false,
    "boundingBoxes": [
      {
        "mx": 0.0,
        "my": 0.0,
        "mz": 0.0,
        "Mx": 16.0,
        "My": 16.0,
        "Mz": 16.0,
        "subtract": false
      }
    ],
    "name": "Spirit plant",
    "specialInfo": [
      "A spiritual plant that cleanses the spiritual state and could heal or uplift you..."
    ],
    "creativeTab": {
      "value": "DECORATIONS"
    },
    "hardness": 0.0,
    "resistance": 1000.0,
    "luminance": 3,
    "unbreakable": false,
    "isSolid": false,
    "isCustomSoundType": false,
    "soundOnStep": {
      "value": "VINE"
    },
    "breakSound": {
      "value": ""
    },
    "stepSound": {
      "value": ""
    },
    "placeSound": {
      "value": ""
    },
    "hitSound": {
      "value": ""
    },
    "fallSound": {
      "value": ""
    },
    "useLootTableForDrops": false,
    "customDrop": {
      "value": ""
    },
    "dropAmount": 1,
    "forceTicking": false,
    "emissiveRendering": true,
    "hasTileEntity": false,
    "isReplaceable": true,
    "colorOnMap": "DEFAULT",
    "creativePickItem": {
      "value": ""
    },
    "offsetType": "XZ",
    "aiPathNodeType": "DEFAULT",
    "flammability": 100,
    "fireSpreadSpeed": 60,
    "jumpFactor": 1.0,
    "speedFactor": 1.0,
    "canBePlacedOn": [
      {
        "value": "Blocks.GRASS"
      },
      {
        "value": "Blocks.STONE#0"
      },
      {
        "value": "Blocks.DIRT#0"
      }
    ],
    "isBonemealable": false,
    "frequencyOnChunks": 1,
    "spawnWorldTypes": [],
    "restrictionBiomes": [],
    "patchSize": 1,
    "generateAtAnyHeight": false,
    "onRandomUpdateEvent": {
      "name": "Partickleupdate"
    },
    "onDestroyedByPlayer": {
      "name": "WeirdUpdateTick"
    }
  }
}